py_obs/__init__.py
py_obs/build_result.py
py_obs/configuration.py
py_obs/history.py
py_obs/logger.py
py_obs/maintenance.py
py_obs/osc.py
py_obs/person.py
py_obs/project.py
py_obs/py.typed
py_obs/request.py
py_obs/service.py
py_obs/status.py
py_obs/token.py
py_obs/xml_factory.py
py_obs-0.0.2.dist-info/METADATA
py_obs-0.0.2.dist-info/WHEEL
py_obs-0.0.2.dist-info/RECORD
