Metadata-Version: 2.3
Name: py-obs
Version: 0.0.2
Summary: Asynchronous API wrapper for the Open Build Service
License: GPL-2.0-or-later
Author: Dan Čermák
Author-email: dcermak@suse.com
Requires-Python: >=3.11,<4.0
Classifier: License :: OSI Approved :: GNU General Public License v2 or later (GPLv2+)
Classifier: Programming Language :: Python :: 3
Classifier: Programming Language :: Python :: 3.11
Classifier: Programming Language :: Python :: 3.12
Classifier: Programming Language :: Python :: 3.13
Requires-Dist: aiohttp (>=3.9)
